tpbla_thermal/__init__.py
tpbla_thermal/cli.py
tpbla_thermal/gui.py
tpbla_thermal-0.0.4.dist-info/METADATA
tpbla_thermal-0.0.4.dist-info/WHEEL
tpbla_thermal-0.0.4.dist-info/entry_points.txt
tpbla_thermal-0.0.4.dist-info/licenses/LICENSE
tpbla_thermal-0.0.4.dist-info/RECORD
