Metadata-Version: 2.4
Name: tpbla-thermal
Version: 0.0.4
Summary: TPBLA_ThermAL: ML for amyloid thermodynamic landscape prediction.
Project-URL: Homepage, https://github.com/conor-mckay98/ThermAL
Project-URL: Issues, https://github.com/conor-mckay98/ThermAL/issues
Author: Conor McKay
License: MIT License
License-File: LICENSE
Classifier: Intended Audience :: Science/Research
Classifier: License :: OSI Approved :: MIT License
Classifier: Operating System :: OS Independent
Classifier: Programming Language :: Python :: 3
Classifier: Programming Language :: Python :: 3 :: Only
Classifier: Programming Language :: Python :: 3.8
Classifier: Topic :: Scientific/Engineering :: Bio-Informatics
Requires-Python: >=3.8
Requires-Dist: joblib
Requires-Dist: matplotlib
Requires-Dist: numpy
Requires-Dist: openpyxl
Requires-Dist: pandas
Requires-Dist: pillow
Requires-Dist: scikit-learn==1.2.2
Requires-Dist: scipy==1.9.3
Requires-Dist: seaborn
